pyautd3_emulator/__init__.py
pyautd3_emulator/emulator.py
pyautd3_emulator/instant.py
pyautd3_emulator/py.typed
pyautd3_emulator/range.py
pyautd3_emulator/record.py
pyautd3_emulator/recorder.py
pyautd3_emulator/rms.py
pyautd3_emulator/bin/autd3capi_emulator.dll
pyautd3_emulator/native_methods/__init__.py
pyautd3_emulator/native_methods/autd3capi_emulator.py
pyautd3_emulator-38.0.0.dist-info/licenses/LICENSE
pyautd3_emulator-38.0.0.dist-info/METADATA
pyautd3_emulator-38.0.0.dist-info/WHEEL
pyautd3_emulator-38.0.0.dist-info/top_level.txt
pyautd3_emulator-38.0.0.dist-info/RECORD
