Metadata-Version: 2.4
Name: pyautd3_emulator
Version: 38.0.0
Summary: autd3-emulator library wrapper for python
Author-email: Shun Suzuki <suzuki@hapis.k.u-tokyo.ac.jp>
License-Expression: MIT
Project-URL: Repository, https://github.com/shinolab/pyautd3_emulator.git
Classifier: Programming Language :: Python :: 3.12
Classifier: Programming Language :: Python :: 3.13
Classifier: Programming Language :: Python :: 3.14
Classifier: Operating System :: Microsoft :: Windows
Classifier: Operating System :: MacOS :: MacOS X
Classifier: Operating System :: POSIX
Requires-Python: >=3.12
License-File: LICENSE
Requires-Dist: numpy>=2.3.4
Requires-Dist: polars>=1
Requires-Dist: pyautd3==38.0.0
Dynamic: license-file
